fast_arrow/__init__.py
fast_arrow/client.py
fast_arrow/exceptions.py
fast_arrow/util.py
fast_arrow/version.py
fast_arrow/option_strategies/__init__.py
fast_arrow/option_strategies/iron_condor.py
fast_arrow/option_strategies/vertical.py
fast_arrow/resources/__init__.py
fast_arrow/resources/account.py
fast_arrow/resources/collection.py
fast_arrow/resources/dividend.py
fast_arrow/resources/option.py
fast_arrow/resources/option_chain.py
fast_arrow/resources/option_event.py
fast_arrow/resources/option_marketdata.py
fast_arrow/resources/option_order.py
fast_arrow/resources/option_position.py
fast_arrow/resources/portfolio.py
fast_arrow/resources/stock.py
fast_arrow/resources/stock_marketdata.py
fast_arrow/resources/stock_order.py
fast_arrow/resources/stock_position.py
fast_arrow/resources/user.py
fast_arrow/ssl_certs/certs.pem
fast_arrow-1.0.3.dist-info/LICENSE
fast_arrow-1.0.3.dist-info/METADATA
fast_arrow-1.0.3.dist-info/WHEEL
fast_arrow-1.0.3.dist-info/top_level.txt
fast_arrow-1.0.3.dist-info/RECORD
