Metadata-Version: 2.1
Name: fast-arrow
Version: 1.0.3
Summary: A simple yet robust API client for Robinhood
Home-page: https://github.com/westonplatter/fast_arrow/
Author: Weston Platter
Author-email: westonplatter@gmail.com
License: MIT License
Project-URL: Issue Tracker, https://github.com/westonplatter/fast_arrow/issues
Project-URL: Source Code, https://github.com/westonplatter/fast_arrow
Platform: UNKNOWN
Requires-Python: >=3.5
Requires-Dist: datetime
Requires-Dist: deprecation
Requires-Dist: pathlib2
Requires-Dist: requests (>=2.20.0)
Requires-Dist: pandas (>=0.23.2)
Requires-Dist: numpy
Requires-Dist: yarl
Requires-Dist: urllib3 (>=1.24.2)
